{
  "ModItems": [
    "Iron Pipe",
    "Gold Pipe",
    "Extractor Pipe",
    "Inserter Pipe",
    "Polymorphic Pipe",
    "Filter Pipe",
    "Chest",
    "Shipping Bin",
    "Mini-Fridge",
    "Invisibilizer"
  ],
  "NetworkItems": [
    "Iron Pipe",
    "Gold Pipe",
    "Extractor Pipe",
    "Inserter Pipe",
    "Polymorphic Pipe",
    "Filter Pipe"
  ],
  "PipeNames": [
    "Iron Pipe",
    "Gold Pipe",
    "Extractor Pipe",
    "Inserter Pipe",
    "Polymorphic Pipe",
    "Filter Pipe"
  ],
  "IOPipeNames": [
    "Extractor Pipe",
    "Inserter Pipe",
    "Polymorphic Pipe",
    "Filter Pipe"
  ],
  "ExtraNames": [
    "Chest",
    "Mini-Fridge"
  ],
  "Buildings": [
    "Shipping Bin"
  ],
  "Locations": [
    "Farm"
  ]

}
