{
  "ModItems": [
    "ConnectorPipe",
    "ExtractorPipe",
    "InserterPipe",
    "PolymorphicPipe",
    "FilterPipe",
    "Chest",
    "Shipping Bin"
  ],
  "NetworkItems": [
    "ConnectorPipe",
    "ExtractorPipe",
    "InserterPipe",
    "PolymorphicPipe",
    "FilterPipe"
  ],
  "PipeNames": [
    "ConnectorPipe",
    "ExtractorPipe",
    "InserterPipe",
    "PolymorphicPipe",
    "FilterPipe"
  ],
  "IOPipeNames": [
    "ExtractorPipe",
    "InserterPipe",
    "PolymorphicPipe",
    "FilterPipe"
  ],
  "ExtraNames": [
    "Chest"
  ],
  "Buildings": [
    "Shipping Bin"
  ],
  "Locations": [
    "Farm"
  ]

}
